crypto_wallet/__init__.py
crypto_wallet-0.1.0.dist-info/DESCRIPTION.rst
crypto_wallet-0.1.0.dist-info/METADATA
crypto_wallet-0.1.0.dist-info/RECORD
crypto_wallet-0.1.0.dist-info/WHEEL
crypto_wallet-0.1.0.dist-info/metadata.json
crypto_wallet-0.1.0.dist-info/top_level.txt
