Metadata-Version: 2.0
Name: crypto-wallet
Version: 0.1.0
Summary: The easiest way to integrate Crypto Wallet Api Functions in your applications. Sign up at Cryptowallet.com for your API key.
Home-page: http://www.osiztechnologies.com/
Author: OsizTech
Author-email: info@osiztechnologies.com
License: ISC
Keywords: CryptoWallet crypto_wallet bitcoin_api crypto wallet crypto_wallet_api
Platform: UNKNOWN
Requires-Dist: base58
Requires-Dist: ecdsa
Requires-Dist: pycrypto
Requires-Dist: requests
Requires-Dist: six
